{
    "activity": 61697,
    "arrow-clockwise": 61698,
    "arrow-left": 61699,
    "arrow-repeat": 61700,
    "arrow-right": 61701,
    "arrow-up-circle-fill": 61702,
    "box-arrow-in-right": 61703,
    "box-arrow-right": 61704,
    "bug": 61705,
    "check-circle-fill": 61706,
    "check-circle": 61707,
    "check-lg": 61708,
    "circle-fill": 61709,
    "cloud-download": 61710,
    "collection": 61711,
    "cpu": 61712,
    "dash-lg": 61713,
    "database": 61714,
    "download": 61715,
    "exclamation-triangle-fill": 61716,
    "exclamation-triangle": 61717,
    "eye": 61718,
    "file-earmark-text": 61719,
    "file-text": 61720,
    "folder": 61721,
    "folder2-open": 61722,
    "gear": 61723,
    "github": 61724,
    "globe": 61725,
    "globe2": 61726,
    "graph-up": 61727,
    "hdd-network": 61728,
    "hdd": 61729,
    "inbox": 61730,
    "info-circle": 61731,
    "journal-text": 61732,
    "key": 61733,
    "lightning-charge-fill": 61734,
    "lightning": 61735,
    "list-check": 61736,
    "list-task": 61737,
    "list-ul": 61738,
    "list": 61739,
    "lock": 61740,
    "memory": 61741,
    "menu-app": 61742,
    "pause": 61743,
    "pc-display": 61744,
    "play-fill": 61745,
    "play": 61746,
    "plus-lg": 61747,
    "question-circle": 61748,
    "router": 61749,
    "save": 61750,
    "search": 61751,
    "shield-check": 61752,
    "shield-lock": 61753,
    "stop-fill": 61754,
    "tag": 61755,
    "terminal": 61756,
    "trash": 61757,
    "wifi": 61758,
    "x-circle-fill": 61759,
    "x-circle": 61760,
    "x-lg": 61761
}